mizar/__init__.py
mizar/api.py
mizar/studio.py
mizar/tests/__init__.py
mizar/tests/test_mizar_api.py
mizar/tests/test_mizar_studio.py
mizar-0.1.5.dist-info/LICENSE
mizar-0.1.5.dist-info/METADATA
mizar-0.1.5.dist-info/WHEEL
mizar-0.1.5.dist-info/top_level.txt
mizar-0.1.5.dist-info/RECORD
