Metadata-Version: 2.1
Name: mizar
Version: 0.1.5
Summary: Official API for the MizarAI platform
Home-page: https://github.com/MizarAI/mizar
Author: MizarAI
Author-email: info@mizar.ai
License: UNKNOWN
Project-URL: Bug Tracker, https://github.com/MizarAI/mizar/issues
Platform: UNKNOWN
Classifier: Programming Language :: Python
Classifier: Programming Language :: Python :: 3
Classifier: Programming Language :: Python :: 3.6
Classifier: Programming Language :: Python :: 3.7
Classifier: Programming Language :: Python :: 3.8
Classifier: License :: OSI Approved :: MIT License
Classifier: Operating System :: OS Independent
Classifier: Natural Language :: English
Classifier: Topic :: Office/Business
Classifier: Topic :: System :: Networking
Classifier: Topic :: Communications :: Chat
Classifier: Intended Audience :: Developers
Requires-Python: >=3.6
License-File: LICENSE
Requires-Dist: requests (>=2.23.0)
Requires-Dist: pandas (==1.2.2)
Requires-Dist: dill (>=0.3.3)
